mininec/Version.py
mininec/__init__.py
mininec/mininec.py
mininec/pulse.py
mininec/segment.py
mininec/taper.py
mininec/util.py
pymininec-1.2.0.dist-info/LICENSE
pymininec-1.2.0.dist-info/METADATA
pymininec-1.2.0.dist-info/WHEEL
pymininec-1.2.0.dist-info/entry_points.txt
pymininec-1.2.0.dist-info/top_level.txt
pymininec-1.2.0.dist-info/RECORD
