Metadata-Version: 2.2
Name: pymininec
Version: 1.2.0
Summary: Python version of the original MININEC Antenna Optimization code
Home-page: https://github.com/schlatterbeck/pymininec
Author: Ralf Schlatterbeck
Author-email: Ralf Schlatterbeck <rsc@runtux.com>
License: MIT License
Project-URL: Homepage, https://github.com/schlatterbeck/pymininec
Project-URL: Bug Tracker, https://github.com/schlatterbeck/pymininec/issues
Platform: Any
Classifier: Development Status :: 5 - Production/Stable
Classifier: License :: OSI Approved :: MIT License
Classifier: Operating System :: OS Independent
Classifier: Intended Audience :: Science/Research
Classifier: Intended Audience :: Other Audience
Classifier: Topic :: Communications :: Ham Radio
Classifier: Programming Language :: Python
Classifier: Programming Language :: Python :: 3.7
Classifier: Programming Language :: Python :: 3.8
Classifier: Programming Language :: Python :: 3.9
Classifier: Programming Language :: Python :: 3.10
Classifier: Programming Language :: Python :: 3.11
Classifier: Programming Language :: Python :: 3.12
Requires-Python: >=3.7
License-File: LICENSE
Requires-Dist: matplotlib
Requires-Dist: numpy
Requires-Dist: scipy
Provides-Extra: test
Requires-Dist: pytest; extra == "test"
Dynamic: author
Dynamic: home-page
Dynamic: platform
Dynamic: requires-python
